data2df/__init__.py
data2df/base.py
data2df/csv.py
data2df/db/__init__.py
data2df/db/base.py
data2df/db/postgres.py
data2df/db/sqlite.py
data2df/db/vertica.py
data2df/geospatial/__init__.py
data2df/geospatial/base.py
data2df/geospatial/geojson.py
data2df/manage_requirements/__init__.py
data2df/manage_requirements/decorator.py
data2df/manage_requirements/typing.py
data2df/parquet.py
data2df/utils/__init__.py
data2df/utils/unstructured_io.py
data2df-0.0.1a9.dist-info/METADATA
data2df-0.0.1a9.dist-info/WHEEL
data2df-0.0.1a9.dist-info/RECORD
