Metadata-Version: 2.1
Name: data2df
Version: 0.0.1a9
Summary: Unified interface to connect common data sources in Data Science with common dataframe packages
Author: Claudio Chiappetta
Author-email: cl4udio.chiappetta@gmail.com
Requires-Python: >=3.10,<3.13
Classifier: Programming Language :: Python :: 3
Classifier: Programming Language :: Python :: 3.10
Classifier: Programming Language :: Python :: 3.11
Requires-Dist: pre-commit (>=3.5.0,<4.0.0)
Requires-Dist: pyyaml (>=6.0.1,<7.0.0)
